pathos_lib_pylogger/__init__.py
pathos_lib_pylogger/pathos_pylogger.py
pathos_lib_pylogger-1.0.9.dist-info/METADATA
pathos_lib_pylogger-1.0.9.dist-info/WHEEL
pathos_lib_pylogger-1.0.9.dist-info/top_level.txt
pathos_lib_pylogger-1.0.9.dist-info/RECORD
